mojo/README.md
mojo/dataprofiles/__init__.py
mojo/dataprofiles/basedataprofile.py
mojo/dataprofiles/couchdbprofile.py
mojo/dataprofiles/databasebasicprofile.py
mojo/dataprofiles/databasebasictcpprofile.py
mojo/dataprofiles/dataprofilemanager.py
mojo/dataprofiles/mongodbatlasprofile.py
mojo/dataprofiles/snowflakeprofile.py
mojo_dataprofiles-2.0.5.dist-info/LICENSE.txt
mojo_dataprofiles-2.0.5.dist-info/METADATA
mojo_dataprofiles-2.0.5.dist-info/WHEEL
mojo_dataprofiles-2.0.5.dist-info/RECORD
